[
    {
        "ModName": "Holland beige curtains - S-Way",
        "ImageSource": "https://i.imgur.com/Ko5iJEP.jpeg",
        "MessageID": 1392860546402877571,
        "UploaderID": "891346545889398845",
        "DownloadURL_EU": "https://sharemods.com/8bmnmg66hp4q/Iveco_sway_courtains_beige.rar.html",
        "DownloadURL_UK": "https://sharemods.com/8bmnmg66hp4q/Iveco_sway_courtains_beige.rar.html"
    },
    {
        "ImageSource": "https://i.imgur.com/2liIqHM.gif",
        "ModName": "S-Way | Animated LED Window Eyes",
        "DownloadURL_UK": "https://modsfire.com/QygM14sD53CMwQI",
        "DownloadURL_EU": "https://modsfire.com/QygM14sD53CMwQI"
    },
    {
        "ImageSource": "https://i.imgur.com/P120MKI.png",
        "ModName": "Iveco Hi-Way - Big GPS",
        "DownloadURL_EU": "https://sharemods.com/s3hlu16dvb4g/Iveco_Big_GPS.zip.html"
    },
    {
        "ImageSource": "https://i.imgur.com/yEfs4HR.png",
        "ModName": "Lightbox and Exhaust",
        "DownloadURL": "https://sharemods.com/i3obh9cgx14y/ivecoext.zip.html"
    }
]